docs/source/conf.py
glpilib2/__init__.py
glpilib2/basic_wrapper.py
glpilib2-1.4.0.dist-info/LICENSE
glpilib2-1.4.0.dist-info/METADATA
glpilib2-1.4.0.dist-info/WHEEL
glpilib2-1.4.0.dist-info/top_level.txt
glpilib2-1.4.0.dist-info/RECORD
