Metadata-Version: 2.2
Name: glpilib2
Version: 1.4.0
Summary: A python library for interacting with GLPI API.
Author-email: Marcelo Lacerda <marceloslacerda@gmail.com>
License:                     GNU GENERAL PUBLIC LICENSE
Project-URL: Homepage, https://github.com/marceloslacerda/glpilib2
Project-URL: Repository, https://github.com/marceloslacerda/glpilib2.git
Project-URL: Issues, https://github.com/marceloslacerda/glpilib2/issues
Classifier: Development Status :: 4 - Beta
Classifier: Intended Audience :: Developers
Classifier: Programming Language :: Python :: 3.10
Classifier: Programming Language :: Python :: 3.11
Classifier: Programming Language :: Python :: 3.12
Classifier: Programming Language :: Python :: 3.13
Requires-Python: >=3.10
License-File: LICENSE
Requires-Dist: requests
Provides-Extra: dev
Requires-Dist: pytest; extra == "dev"
Requires-Dist: numpydoc; extra == "dev"
Requires-Dist: sphinx; extra == "dev"
